setup.py
fconfig/__init__.py
fconfig/builder.py
fconfig/common.py
fconfig/config.py
fconfig/config_data_object.py
fconfig/config_property.py
fconfig/configuration.py
fconfig/init.py
fconfig/java.py
fconfig/loader.py
fconfig/merger.py
fconfig/parser.py
fconfig/resolver.py
fconfig.egg-info/PKG-INFO
fconfig.egg-info/SOURCES.txt
fconfig.egg-info/dependency_links.txt
fconfig.egg-info/requires.txt
fconfig.egg-info/top_level.txt
fconfig/templates/__init__.py
fconfig/templates/config_template-old.txt
fconfig/templates/config_template.txt
fconfig/test/__init__.py
fconfig/test/builder_complete_test.py
fconfig/test/builder_test.py
fconfig/test/common.py
fconfig/test/parser_test.py
fconfig/test/resolver_test.py
fconfig/test/resources/__init__.py
fconfig/test/resources/builder/__init__.py
fconfig/test/resources/builder/array_of_objects-array.py
fconfig/test/resources/builder/array_of_objects-object.py
fconfig/test/resources/builder/array_test.py
fconfig/test/resources/builder/array_test_root.py
fconfig/test/resources/builder/one_var.py
fconfig/test/resources/builder/string_array_in_object-array.py
fconfig/test/resources/builder/string_array_in_object-root.py