Metadata-Version: 1.2
Name: fconfig
Version: 1.1.0
Summary: Python config loader for Future Config format.
Home-page: https://github.com/F-I-D-O/Future-Config/
Author: F.I.D.O.
Author-email: david.fido.fiedler@gmail.com
License: MIT
Platform: UNKNOWN
Requires-Python: >=3
